starlette_dataframe_response/__init__.py
starlette_dataframe_response/__main__.py
starlette_dataframe_response/dataset.py
starlette_dataframe_response/distribute.py
starlette_dataframe_response-0.0.0.dist-info/METADATA
starlette_dataframe_response-0.0.0.dist-info/WHEEL
starlette_dataframe_response-0.0.0.dist-info/top_level.txt
starlette_dataframe_response-0.0.0.dist-info/RECORD
