Metadata-Version: 2.1
Name: starlette-dataframe-response
Version: 0.0.0
Summary: Convenient, but not fast
Home-page: https://github.com/podhmo/starlette-dataframe-response
Author: podhmo
Author-email: ababjam61+github@gmail.com
License: UNKNOWN
Platform: UNKNOWN
Classifier: Programming Language :: Python :: 3
Classifier: Development Status :: 3 - Alpha
Requires-Python: >3.7
Requires-Dist: starlette
Requires-Dist: pandas
Requires-Dist: typing-extensions
Provides-Extra: dev
Requires-Dist: black ; extra == 'dev'
Requires-Dist: flake8 ; extra == 'dev'
Requires-Dist: mypy ; extra == 'dev'
Provides-Extra: fullset
Requires-Dist: tabulate ; extra == 'fullset'
Requires-Dist: vega-datasets ; extra == 'fullset'
Requires-Dist: uvicorn ; extra == 'fullset'
Provides-Extra: testing
Requires-Dist: pytest ; extra == 'testing'
Requires-Dist: tabulate ; extra == 'testing'
